autoprof/Pipeline.py
autoprof/__init__.py
autoprof/_version.py
autoprof/autoprof.py
autoprof/autoprofutils/Diagnostic_Plots.py
autoprof/autoprofutils/ImageTransform.py
autoprof/autoprofutils/SharedFunctions.py
autoprof/autoprofutils/__init__.py
autoprof/media/AP_logo.png
autoprof/media/AP_logo_white.png
autoprof/media/__init__.py
autoprof/pipeline_steps/Axial_Profiles.py
autoprof/pipeline_steps/Background.py
autoprof/pipeline_steps/Center.py
autoprof/pipeline_steps/Check_Fit.py
autoprof/pipeline_steps/Ellipse_Model.py
autoprof/pipeline_steps/Isophote_Extract.py
autoprof/pipeline_steps/Isophote_Fit.py
autoprof/pipeline_steps/Isophote_Initialize.py
autoprof/pipeline_steps/Mask.py
autoprof/pipeline_steps/PSF.py
autoprof/pipeline_steps/Plotting_Steps.py
autoprof/pipeline_steps/Radial_Profiles.py
autoprof/pipeline_steps/Slice_Profiles.py
autoprof/pipeline_steps/Write_Fi.py
autoprof/pipeline_steps/Write_Prof.py
autoprof/pipeline_steps/__init__.py
autoprof-1.3.4.dist-info/METADATA
autoprof-1.3.4.dist-info/WHEEL
autoprof-1.3.4.dist-info/entry_points.txt
autoprof-1.3.4.dist-info/licenses/LICENSE
autoprof-1.3.4.dist-info/RECORD
