Metadata-Version: 2.4
Name: autoprof
Version: 1.3.4
Summary: Fast, robust, deep isophotal solutions for galaxy images.
Project-URL: Homepage, https://autostronomy.github.io/AutoProf/
Project-URL: Documentation, https://autoprof.readthedocs.io
Project-URL: Repository, https://github.com/Autostronomy/AutoProf
Project-URL: Issues, https://github.com/Autostronomy/AutoProf/issues
Author-email: Connor Stone <connorstone628@gmail.com>
License:                     GNU GENERAL PUBLIC LICENSE
License-File: LICENSE
Keywords: astronomy,astrophysics,autoprof,photometry,scientific computing
Classifier: Development Status :: 5 - Production/Stable
Classifier: Intended Audience :: Science/Research
Classifier: License :: OSI Approved :: GNU General Public License v3 (GPLv3)
Classifier: Operating System :: OS Independent
Classifier: Programming Language :: Python :: 3
Requires-Python: >=3.9
Requires-Dist: astropy<6.0,>=3.2.3
Requires-Dist: matplotlib>=3.1.2
Requires-Dist: numpy<2.0,>=1.17.4
Requires-Dist: photutils<=1.5.0,>=0.7.2
Requires-Dist: scikit-learn>=0.21.3
Requires-Dist: scipy>=1.3.3
